gerabaldi/__init__.py
gerabaldi/exceptions.py
gerabaldi/helpers.py
gerabaldi/sim.py
gerabaldi/cookbook/__init__.py
gerabaldi/cookbook/mech_mdls.py
gerabaldi/cookbook/test_envs.py
gerabaldi/cookbook/test_specs.py
gerabaldi/math/__init__.py
gerabaldi/math/minimize.py
gerabaldi/models/__init__.py
gerabaldi/models/devices.py
gerabaldi/models/phys_envs.py
gerabaldi/models/random_vars.py
gerabaldi/models/reports.py
gerabaldi/models/states.py
gerabaldi/models/test_specs.py
gerabaldi-0.2.0.dist-info/LICENSE
gerabaldi-0.2.0.dist-info/METADATA
gerabaldi-0.2.0.dist-info/WHEEL
gerabaldi-0.2.0.dist-info/top_level.txt
gerabaldi-0.2.0.dist-info/RECORD
