Metadata-Version: 2.1
Name: gerabaldi
Version: 0.2.0
Summary: A temporal simulator for probabilistic degradation and failure processes with a focus on integrated circuit wear-out 
Author-email: Ian Hill <ianrmhill@gmail.com>
Project-URL: Homepage, https://github.com/ianrmhill/gerabaldi
Classifier: Programming Language :: Python :: 3
Classifier: License :: OSI Approved :: Apache Software License
Classifier: Operating System :: OS Independent
Classifier: Topic :: Scientific/Engineering :: Physics
Classifier: Intended Audience :: Science/Research
Classifier: Development Status :: 3 - Alpha
Requires-Python: >=3.8
License-File: LICENSE
Requires-Dist: numpy <2.0.0,>=1.24.2
Requires-Dist: pandas >=2.0.0
Requires-Dist: coloredlogs >=15.0.1
Requires-Dist: scipy <1.13 ; python_version == "3.9"
